climalab/__init__.py
climalab/meteorological/__init__.py
climalab/meteorological/variables.py
climalab/meteorological/weather_software.py
climalab/netcdf_tools/__init__.py
climalab/netcdf_tools/cdo_tools.py
climalab/netcdf_tools/detect_faulty.py
climalab/netcdf_tools/extract_basics.py
climalab/netcdf_tools/nco_tools.py
climalab/supplementary_tools/__init__.py
climalab/supplementary_tools/auxiliary_functions.py
climalab/supplementary_tools/ba_mean.py
climalab/supplementary_tools/ba_mean_and_var.py
climalab/supplementary_tools/ba_nonparametric_qm.py
climalab/supplementary_tools/ba_parametric_qm.py
climalab/supplementary_tools/basic_mapplot.py
climalab/supplementary_tools/basic_plot.py
climalab/supplementary_tools/comparison_lineplot.py
climalab/supplementary_tools/eval_original.py
climalab/supplementary_tools/temperature_map.py
climalab-4.6.7.dist-info/licenses/LICENSE
climalab-4.6.7.dist-info/METADATA
climalab-4.6.7.dist-info/WHEEL
climalab-4.6.7.dist-info/top_level.txt
climalab-4.6.7.dist-info/RECORD
