Metadata-Version: 2.4
Name: climalab
Version: 4.6.7
Summary: A Python toolkit for climate data processing and analysis
Author-email: Jon Ander Gabantxo <jagabantxo@gmail.com>
License: MIT License
Project-URL: Homepage, https://github.com/EusDancerDev/climalab
Project-URL: Documentation, https://github.com/EusDancerDev/climalab#readme
Project-URL: Repository, https://github.com/EusDancerDev/climalab.git
Project-URL: Bug Reports, https://github.com/EusDancerDev/climalab/issues
Keywords: climate,meteorology,atmospheric science,data analysis,climate data
Classifier: Development Status :: 4 - Beta
Classifier: Intended Audience :: Science/Research
Classifier: Topic :: Scientific/Engineering :: Atmospheric Science
Classifier: Programming Language :: Python :: 3
Classifier: Programming Language :: Python :: 3.10
Classifier: Programming Language :: Python :: 3.11
Classifier: Programming Language :: Python :: 3.12
Classifier: Operating System :: POSIX :: Linux
Requires-Python: >=3.10
License-File: LICENSE
Requires-Dist: numpy>=1.21.0
Requires-Dist: pandas>=1.3.0
Requires-Dist: xarray>=2024.2.0
Requires-Dist: netCDF4>=1.6.0
Requires-Dist: matplotlib>=3.8.0
Requires-Dist: cartopy>=0.20.0
Provides-Extra: dev
Requires-Dist: pytest>=7.0.0; extra == "dev"
Requires-Dist: pytest-cov>=4.0.0; extra == "dev"
Requires-Dist: black>=23.0.0; extra == "dev"
Requires-Dist: isort>=5.0.0; extra == "dev"
Requires-Dist: mypy>=1.0.0; extra == "dev"
Requires-Dist: flake8>=6.0.0; extra == "dev"
Dynamic: license-file
